tensorflow_estimator/__init__.py
tensorflow_estimator/_api/__init__.py
tensorflow_estimator/_api/v1/__init__.py
tensorflow_estimator/_api/v1/v1.py
tensorflow_estimator/_api/v1/estimator/__init__.py
tensorflow_estimator/_api/v1/estimator/experimental/__init__.py
tensorflow_estimator/_api/v1/estimator/export/__init__.py
tensorflow_estimator/_api/v1/estimator/inputs/__init__.py
tensorflow_estimator/_api/v1/estimator/tpu/__init__.py
tensorflow_estimator/_api/v1/estimator/tpu/experimental/__init__.py
tensorflow_estimator/_api/v2/__init__.py
tensorflow_estimator/_api/v2/v2.py
tensorflow_estimator/_api/v2/estimator/__init__.py
tensorflow_estimator/_api/v2/estimator/experimental/__init__.py
tensorflow_estimator/_api/v2/estimator/export/__init__.py
tensorflow_estimator/_api/v2/estimator/inputs/__init__.py
tensorflow_estimator/python/__init__.py
tensorflow_estimator/python/estimator/__init__.py
tensorflow_estimator/python/estimator/early_stopping.py
tensorflow_estimator/python/estimator/estimator.py
tensorflow_estimator/python/estimator/estimator_lib.py
tensorflow_estimator/python/estimator/exporter.py
tensorflow_estimator/python/estimator/extenders.py
tensorflow_estimator/python/estimator/gc.py
tensorflow_estimator/python/estimator/keras.py
tensorflow_estimator/python/estimator/mode_keys.py
tensorflow_estimator/python/estimator/model_fn.py
tensorflow_estimator/python/estimator/run_config.py
tensorflow_estimator/python/estimator/training.py
tensorflow_estimator/python/estimator/util.py
tensorflow_estimator/python/estimator/api/__init__.py
tensorflow_estimator/python/estimator/api/_v1/__init__.py
tensorflow_estimator/python/estimator/api/_v1/v1.py
tensorflow_estimator/python/estimator/api/_v1/estimator/__init__.py
tensorflow_estimator/python/estimator/api/_v1/estimator/experimental/__init__.py
tensorflow_estimator/python/estimator/api/_v1/estimator/export/__init__.py
tensorflow_estimator/python/estimator/api/_v1/estimator/inputs/__init__.py
tensorflow_gpu_estimator-2.1.0.dist-info/METADATA
tensorflow_gpu_estimator-2.1.0.dist-info/WHEEL
tensorflow_gpu_estimator-2.1.0.dist-info/top_level.txt
tensorflow_gpu_estimator-2.1.0.dist-info/RECORD
